Ingine/__init__.py
Ingine/ann.py
Ingine/ga.py
Ingine/examples/__init__.py
Ingine/examples/boston_housing.py
Ingine/examples/data.py
Ingine/examples/digit_recognition.py
Ingine/examples/eight_queens_puzzle.py
Ingine/examples/generate_data.py
Ingine/examples/salesman_issue.py
Ingine/examples/seabattle.py
Ingine/examples/seabattle_engine.py
ingine/__init__.py
ingine/ann.py
ingine/ga.py
ingine/examples/__init__.py
ingine/examples/boston_housing.py
ingine/examples/data.py
ingine/examples/digit_recognition.py
ingine/examples/eight_queens_puzzle.py
ingine/examples/generate_data.py
ingine/examples/object_recognition.py
ingine/examples/salesman_issue.py
ingine/examples/seabattle.py
ingine/examples/seabattle_engine.py
ingine-0.1.7.dist-info/LICENSE
ingine-0.1.7.dist-info/METADATA
ingine-0.1.7.dist-info/WHEEL
ingine-0.1.7.dist-info/top_level.txt
ingine-0.1.7.dist-info/RECORD
