Metadata-Version: 2.1
Name: ingine
Version: 0.1.7
Summary: A cross-platform library for easy-access AI tools
Home-page: https://github.com/sqarrt/ingine
Author: sqarrt
Author-email: sqarrt1337@gmail.com
License: UNKNOWN
Platform: UNKNOWN
Classifier: Programming Language :: Python :: 3
Classifier: License :: OSI Approved :: MIT License
Classifier: Operating System :: OS Independent
Classifier: Natural Language :: Russian
Requires-Dist: keras
Requires-Dist: numpy
Requires-Dist: tensorflow
Requires-Dist: theano
Requires-Dist: pyeasyga
